supervisoragent/__init__.py
supervisoragent/agent.py
supervisoragent/eventlistener.py
supervisoragent/eventmonitor.py
supervisoragent/log.py
supervisoragent/processmonitor.py
supervisoragent/procstat.py
supervisoragent/rpc.py
supervisoragent/systemstat.py
supervisoragent/ws.py
supervisoragent/config/__init__.py
supervisoragent/config/agent.py
supervisoragent/data/conf/supervisoragent.conf
supervisoragent/data/supervisor/supervisoragent.conf
supervisoragent-0.0.1.dev2.dist-info/DESCRIPTION.rst
supervisoragent-0.0.1.dev2.dist-info/entry_points.txt
supervisoragent-0.0.1.dev2.dist-info/METADATA
supervisoragent-0.0.1.dev2.dist-info/metadata.json
supervisoragent-0.0.1.dev2.dist-info/RECORD
supervisoragent-0.0.1.dev2.dist-info/top_level.txt
supervisoragent-0.0.1.dev2.dist-info/WHEEL
