Metadata-Version: 2.0
Name: supervisoragent
Version: 0.0.1.dev2
Summary: An agent for monitoring applications run by supervisor
Home-page: https://github.com/silverfernsys/supervisoragent
Author: Silver Fern Systems
Author-email: dev@silverfern.io
License: BSD
Keywords: monitoring development
Platform: UNKNOWN
Classifier: Development Status :: 3 - Alpha
Classifier: Intended Audience :: Developers
Classifier: Topic :: Software Development :: Build Tools
Classifier: License :: OSI Approved :: BSD License
Classifier: Programming Language :: Python :: 2.7
Requires-Dist: configutil
Requires-Dist: psutil
Requires-Dist: setproctitle
Requires-Dist: websocket-client
Provides-Extra: test
Requires-Dist: coverage; extra == 'test'
Requires-Dist: codecov; extra == 'test'
Requires-Dist: pytest; extra == 'test'
Requires-Dist: mock; extra == 'test'
